[
  {
    "name": "example1",
    "status": "available",
    "location": "n1",
    "owner": "user1",
    "owner_id": null,
    "genre": "マンガ",
    "borrower": null
  },
  {
    "name": "example2",
    "status": "available",
    "location": "n2",
    "owner": "user2",
    "owner_id": null,
    "genre": "ライトノベル",
    "borrower": null
  },
  {
    "name": "example3",
    "status": "available",
    "location": "n3",
    "owner": "user3",
    "owner_id": null,
    "genre": "小説",
    "borrower": null
  },
  {
    "name": "example4",
    "status": "available",
    "location": "n4",
    "owner": "user4",
    "owner_id": null,
    "genre": "その他",
    "borrower": null
  },
  {
    "name": "ドラえもん1巻",
    "status": "available",
    "location": "私の家",
    "owner": "足立恭一朗",
    "owner_id": null,
    "genre": "マンガ",
    "borrower": null
  },
  {
    "name": "存在しない本",
    "status": "available",
    "location": "知るかボケ",
    "owner": "ｼﾙｶﾎﾞｹ",
    "owner_id": null,
    "genre": "その他",
    "borrower": null
  },
  {
    "name": "殺し屋の営業術",
    "status": "using",
    "location": "M2-2",
    "owner": "83近藤智貴",
    "owner_id": "1360130757770870915",
    "genre": "小説",
    "borrower": {
      "email": "n073864@stg.nada.ac.jp",
      "name": "近藤智貴",
      "className": "2年2組"
    }
  }
]